clusterking_physics/__init__.py
clusterking_physics/version.txt
clusterking_physics/models/__init__.py
clusterking_physics/models/bdlnu/__init__.py
clusterking_physics/models/bdlnu/amplitude.py
clusterking_physics/models/bdlnu/distribution.py
clusterking_physics/models/bdlnu/form_factors.py
clusterking_physics/models/bdlnu/inputs.py
clusterking_physics-0.1.2.dist-info/METADATA
clusterking_physics-0.1.2.dist-info/RECORD
clusterking_physics-0.1.2.dist-info/WHEEL
clusterking_physics-0.1.2.dist-info/top_level.txt
