Metadata-Version: 2.1
Name: clusterking-physics
Version: 0.1.2
Summary: Physics distributions to be clustered by the ClusterKinG package.
Home-page: https://github.com/clusterking/clusterking_physics
License: MIT
Project-URL: Bug Tracker, https://github.com/clusterking/clusterking_physics/issues
Project-URL: Source Code, https://github.com/clusterking/clusterking_physics/
Keywords: clustering,cluster,kinematics,cluster-analysis,machine-learning,ml,hep,hep-ml,hep-ex,hep-ph,wilson,clusterking
Platform: UNKNOWN
Classifier: Programming Language :: Python :: 3
Classifier: License :: OSI Approved :: MIT License
Classifier: Operating System :: OS Independent
Classifier: Topic :: Scientific/Engineering :: Physics
Requires-Dist: numpy
Requires-Dist: flavio
